OneFlow/__init__.py
robotframework_oneflow-0.1.4.dist-info/METADATA
robotframework_oneflow-0.1.4.dist-info/WHEEL
robotframework_oneflow-0.1.4.dist-info/RECORD
