Metadata-Version: 2.3
Name: robotframework-oneflow
Version: 0.1.4
Summary: Robot Framework library to treat a test suite as a one flow, where if any test case will fail than it skip the rest of the tests
License: MIT
Author: otemek
Author-email: etombsc@gmail.com
Requires-Python: >=3.9
Classifier: License :: OSI Approved :: MIT License
Classifier: Programming Language :: Python :: 3
Classifier: Programming Language :: Python :: 3.9
Classifier: Programming Language :: Python :: 3.10
Classifier: Programming Language :: Python :: 3.11
Classifier: Programming Language :: Python :: 3.12
Classifier: Programming Language :: Python :: 3.13
Requires-Dist: robotframework (>=6)
Project-URL: Homepage, https://github.com/otemek/robotframework-oneflow
Project-URL: Issues, https://github.com/otemek/robotframework-oneflow/issues
